setup.cfg
setup.py
Worzis_tools/__init__.py
Worzis_tools/проверка_элементов.py
Worzis_tools/работа_с_файлом.py
Worzis_tools/создание тестов содержимого.py
Worzis_tools/терминал4.py
Worzis_tools/тест.py
Worzis_tools/тесты теории.py
Worzis_tools.egg-info/PKG-INFO
Worzis_tools.egg-info/SOURCES.txt
Worzis_tools.egg-info/dependency_links.txt
Worzis_tools.egg-info/not-zip-safe
Worzis_tools.egg-info/requires.txt
Worzis_tools.egg-info/top_level.txt